markets_analytics/__init__.py
markets_analytics/connectors.py
markets_analytics/dateutil.py
markets_analytics/email.py
markets_analytics/etl.py
markets_analytics/google_chat.py
markets_analytics/gsheet_helper.py
markets_analytics-1.0.1.dist-info/METADATA
markets_analytics-1.0.1.dist-info/WHEEL
markets_analytics-1.0.1.dist-info/licenses/LICENSE
markets_analytics-1.0.1.dist-info/RECORD
