Metadata-Version: 2.3
Name: markets_analytics
Version: 1.0.1
Summary: A utility package to handle data analytics
Project-URL: Homepage, https://github.bus.zalan.do/lounge-sales-markets/markets_analytics
Project-URL: Issues, https://github.bus.zalan.do/lounge-sales-markets/markets_analytics/issues
Author-email: Danyal Imran <markets-analytics@zalando-lounge.de>
License-File: LICENSE
Classifier: License :: OSI Approved :: MIT License
Classifier: Operating System :: OS Independent
Classifier: Programming Language :: Python :: 3
Requires-Python: >=3.8
